setup.cfg
setup.py
pwmd/__init__.py
pwmd/multi.py
pwmd/url.py
pwmd.egg-info/PKG-INFO
pwmd.egg-info/SOURCES.txt
pwmd.egg-info/dependency_links.txt
pwmd.egg-info/entry_points.txt
pwmd.egg-info/not-zip-safe
pwmd.egg-info/requires.txt
pwmd.egg-info/top_level.txt