Metadata-Version: 1.0
Name: pwmd
Version: 0.1
Summary: Multi Database Support For PeeWee
Home-page: UNKNOWN
Author: Young King
Author-email: yanckin@gmail.com
License: BSD
Keywords: multi database orm peewee
Platform: UNKNOWN
